[
    {
        "app_id": "mate-appearance-properties.desktop",
        "date_created": 1581023874.0,
        "description": "After I downloaded it touch pad settings started getting messed and I think I even saw the camera light turn on for a very brief split second. VERY SKECHTY",
        "distro": "Ubuntu",
        "karma_down": 0,
        "karma_up": 0,
        "locale": "en_US",
        "rating": 20,
        "reported": 0,
        "review_id": 147724,
        "score": 0,
        "summary": "Horrible DO NOT GET",
        "user_display": "Marco",
        "user_hash": "0cfc364f96074f8dd0034d1b4e0b4b60face2676",
        "user_skey": "66088287f932dd9c11423e554aad8577a37316b2",
        "version": "1.20.2"
    },
    {
        "app_id": "mate-appearance-properties.desktop",
        "date_created": 1583336203.0,
        "description": "didnt do what i wanted and now i cant uninstall it",
        "distro": "Ubuntu",
        "karma_down": 0,
        "karma_up": 0,
        "locale": "en_GB",
        "rating": 20,
        "reported": 0,
        "review_id": 159859,
        "score": 0,
        "summary": "doesnt uninstall",
        "user_display": "Connor",
        "user_hash": "870dae5bb8292503047102647aaa1d6b623b0b59",
        "user_skey": "66088287f932dd9c11423e554aad8577a37316b2",
        "version": "1.20.2"
    }
]